libdyson_mqtt/__init__.py
libdyson_mqtt/client.py
libdyson_mqtt/exceptions.py
libdyson_mqtt/models.py
libdyson_mqtt/py.typed
libdyson_mqtt-0.2.1.dist-info/licenses/LICENSE
libdyson_mqtt-0.2.1.dist-info/METADATA
libdyson_mqtt-0.2.1.dist-info/WHEEL
libdyson_mqtt-0.2.1.dist-info/top_level.txt
libdyson_mqtt-0.2.1.dist-info/RECORD
