Metadata-Version: 2.4
Name: libdyson-mqtt
Version: 0.2.1
Summary: Python library for MQTT communication with Dyson devices
Author-email: cmgrayb <cmgrayb@users.noreply.github.com>
License: MIT
Project-URL: Homepage, https://github.com/cmgrayb/libdyson-mqtt
Project-URL: Bug Tracker, https://github.com/cmgrayb/libdyson-mqtt/issues
Classifier: Development Status :: 3 - Alpha
Classifier: Intended Audience :: Developers
Classifier: License :: OSI Approved :: MIT License
Classifier: Programming Language :: Python :: 3
Classifier: Programming Language :: Python :: 3.9
Classifier: Programming Language :: Python :: 3.10
Classifier: Programming Language :: Python :: 3.11
Classifier: Programming Language :: Python :: 3.12
Classifier: Programming Language :: Python :: 3.13
Classifier: Topic :: Home Automation
Classifier: Topic :: Software Development :: Libraries :: Python Modules
Requires-Python: >=3.9
License-File: LICENSE
Requires-Dist: paho-mqtt==2.1.0
Requires-Dist: typing-extensions>=4.0.0; python_version < "3.10"
Provides-Extra: dev
Requires-Dist: black==25.1.0; extra == "dev"
Requires-Dist: flake8==7.3.0; extra == "dev"
Requires-Dist: isort==6.0.1; extra == "dev"
Requires-Dist: pytest==8.4.1; extra == "dev"
Requires-Dist: pytest-cov==6.2.1; extra == "dev"
Requires-Dist: mypy==1.17.1; extra == "dev"
Requires-Dist: types-requests==2.32.4.20250809; extra == "dev"
Requires-Dist: types-cryptography==3.3.23.2; extra == "dev"
Requires-Dist: bandit[toml]==1.8.0; extra == "dev"
Requires-Dist: build>=0.10.0; extra == "dev"
Requires-Dist: twine>=4.0.0; extra == "dev"
Dynamic: license-file
